memory_service_client/__init__.py
memory_service_client/cli.py
memory_service_client/client.py
memory_service_client/rag_service_pb2.py
memory_service_client/rag_service_pb2_grpc.py
memory_service_client-0.3.0.dist-info/METADATA
memory_service_client-0.3.0.dist-info/WHEEL
memory_service_client-0.3.0.dist-info/entry_points.txt
memory_service_client-0.3.0.dist-info/top_level.txt
memory_service_client-0.3.0.dist-info/RECORD
